[
  {
    "Rank": 1,
    "Change": "+1",
    "Thumbnail": "https://i.ytimg.com/vi/9mvJPTiuiQg/hqdefault.jpg",
    "Title": "I'M SORRY LA KNIGHT",
    "Channel": "IShowSpeed",
    "Category": "Gaming",
    "Format": "Short",
    "Views Gained": 41408732
  },
  {
    "Rank": 2,
    "Change": "-1",
    "Thumbnail": "https://i.ytimg.com/vi/8cUT9avtEJs/hqdefault.jpg",
    "Title": "Smiti Papa Se Parishan Hogai 🥺🤣#shortsfeed #funny #viral",
    "Channel": "Minakshi xyz",
    "Category": "Entertainment",
    "Format": "Short",
    "Views Gained": 36456471
  },
  {
    "Rank": 3,
    "Change": "+1",
    "Thumbnail": "https://i.ytimg.com/vi/YdSqLx5M7pc/hqdefault.jpg",
    "Title": "Build a Funny Body Game! 🧩😄 | Fun Kids Learning",
    "Channel": "Toony Friends TV",
    "Category": "Entertainment",
    "Format": "Short",
    "Views Gained": 35167383
  },
  {
    "Rank": 4,
    "Change": "+1",
    "Thumbnail": "https://i.ytimg.com/vi/JhbBDhUYvAc/hqdefault.jpg",
    "Title": "very nice funny photography #funny #photographer #streetphotography",
    "Channel": "Feng Family Photography Studio - Feng Xueren",
    "Category": "People & Blogs",
    "Format": "Short",
    "Views Gained": 31287344
  },
  {
    "Rank": 5,
    "Change": "+5",
    "Thumbnail": "https://i.ytimg.com/vi/4Bd8JQI9pg4/hqdefault.jpg",
    "Title": "Sigma Girl Power #funny #sigma #comedy",
    "Channel": "CRAZY GREAPA",
    "Category": "Entertainment",
    "Format": "Short",
    "Views Gained": 21379778
  },
  {
    "Rank": 6,
    "Change": "+11",
    "Thumbnail": "https://i.ytimg.com/vi/QF5YpZI1wnk/hqdefault.jpg",
    "Title": "I Survived 100 Days in Skyblock",
    "Channel": "MrBeast Gaming",
    "Category": "Gaming",
    "Format": "Long",
    "Views Gained": 20889189
  },
  {
    "Rank": 7,
    "Change": "+1",
    "Thumbnail": "https://i.ytimg.com/vi/ygYPwsjyCzQ/hqdefault.jpg",
    "Title": "KISS OF LIFE (키스오브라이프) 'Who is she' Official Music Video",
    "Channel": "KISS OF LIFE",
    "Category": "Music",
    "Format": "Standard",
    "Views Gained": 20066786
  },
  {
    "Rank": 8,
    "Change": "-5",
    "Thumbnail": "https://i.ytimg.com/vi/_JUlWtSCNbs/hqdefault.jpg",
    "Title": "Who's The Strongest Streamer?",
    "Channel": "MrBeast",
    "Category": "Entertainment",
    "Format": "Short",
    "Views Gained": 19026689
  },
  {
    "Rank": 9,
    "Change": "-3",
    "Thumbnail": "https://i.ytimg.com/vi/GGa1zPQZUU8/hqdefault.jpg",
    "Title": "Spiciest Ramen to Escape @patrickzeinali @ChefRush",
    "Channel": "albert_cancook",
    "Category": "Howto & Style",
    "Format": "Short",
    "Views Gained": 18557818
  },
  {
    "Rank": 10,
    "Change": "+4",
    "Thumbnail": "https://i.ytimg.com/vi/wjZ9sBveAIw/hqdefault.jpg",
    "Title": "#gugugaga #咕咕嘎嘎 #明日方舟 #arknights #cute",
    "Channel": "GugaGuga",
    "Category": "People & Blogs",
    "Format": "Short",
    "Views Gained": 18071859
  },
  {
    "Rank": 11,
    "Change": "-2",
    "Thumbnail": "https://i.ytimg.com/vi/_gyultVTesk/hqdefault.jpg",
    "Title": "BTS (방탄소년단) '2.0' Official MV",
    "Channel": "HYBE LABELS",
    "Category": "Music",
    "Format": "Standard",
    "Views Gained": 16730782
  },
  {
    "Rank": 12,
    "Change": "0",
    "Thumbnail": "https://i.ytimg.com/vi/hfSAbl-KnAo/hqdefault.jpg",
    "Title": "Unbelievable things just happened!#shorts #fyp #funny #illusion #plottwist",
    "Channel": "Happy Camp",
    "Category": "People & Blogs",
    "Format": "Short",
    "Views Gained": 16005334
  },
  {
    "Rank": 13,
    "Change": "+7",
    "Thumbnail": "https://i.ytimg.com/vi/YRCpYGOGsts/hqdefault.jpg",
    "Title": "Bandel bgt sih!! #dellaseptt #dailylife #funny #lucu #comedy #ngakak #pov #funnycomedy #dailyvlog",
    "Channel": "Della Septiani",
    "Category": "People & Blogs",
    "Format": "Short",
    "Views Gained": 14747599
  },
  {
    "Rank": 14,
    "Change": "+5",
    "Thumbnail": "https://i.ytimg.com/vi/diBO0gMuTXo/hqdefault.jpg",
    "Title": "BTS (방탄소년단) 'Hooligan' Official MV",
    "Channel": "HYBE LABELS",
    "Category": "Music",
    "Format": "Standard",
    "Views Gained": 14698000
  },
  {
    "Rank": 15,
    "Change": "+3",
    "Thumbnail": "https://i.ytimg.com/vi/ZQnI5gQCAz4/hqdefault.jpg",
    "Title": "アメリカンドッグ vs 映画 Intro IB : @B@BayashiTV_",
    "Channel": "Izu💪🏼イズ",
    "Category": "People & Blogs",
    "Format": "Short",
    "Views Gained": 14404250
  },
  {
    "Rank": 16,
    "Change": "-5",
    "Thumbnail": "https://i.ytimg.com/vi/aAWNuu3ADUI/hqdefault.jpg",
    "Title": "Ranking The Perfect Accuracy Moments",
    "Channel": "Ranzy",
    "Category": "People & Blogs",
    "Format": "Short",
    "Views Gained": 12515979
  },
  {
    "Rank": 17,
    "Change": "+4",
    "Thumbnail": "https://i.ytimg.com/vi/T4tdkvNw76c/hqdefault.jpg",
    "Title": "Jbl go4 speaker drop in water pool bass testing",
    "Channel": "Super bass jbl",
    "Category": "People & Blogs",
    "Format": "Short",
    "Views Gained": 12095387
  },
  {
    "Rank": 18,
    "Change": "-11",
    "Thumbnail": "https://i.ytimg.com/vi/JBBD5JA2Ykc/hqdefault.jpg",
    "Title": "Can We Escape The Police?",
    "Channel": "Topper Guild",
    "Category": "Entertainment",
    "Format": "Short",
    "Views Gained": 12019581
  },
  {
    "Rank": 19,
    "Change": "+4",
    "Thumbnail": "https://i.ytimg.com/vi/AjFk1cY265I/hqdefault.jpg",
    "Title": "Digital Circus Ep 9 Finale [TRAILER]",
    "Channel": "GLITCH",
    "Category": "Film & Animation",
    "Format": "Short",
    "Views Gained": 11902244
  },
  {
    "Rank": 20,
    "Change": "-7",
    "Thumbnail": "https://i.ytimg.com/vi/l5Qgjn7D9r0/hqdefault.jpg",
    "Title": "IShowSpeed Attacks LA Knight with Brass Knuckles🥵😱||#wwe #shorts #shortsfeed #wweshorts #viralvideo",
    "Channel": "Rhea Edit01 ",
    "Category": "Sports",
    "Format": "Short",
    "Views Gained": 11419273
  },
  {
    "Rank": 21,
    "Change": "+1",
    "Thumbnail": "https://i.ytimg.com/vi/KWoTyfPsqbE/hqdefault.jpg",
    "Title": "Sabrina Carpenter - House Tour (Official Video)",
    "Channel": "SabrinaCarpenterVEVO",
    "Category": "Music",
    "Format": "Standard",
    "Views Gained": 11320887
  },
  {
    "Rank": 22,
    "Change": "+3",
    "Thumbnail": "https://i.ytimg.com/vi/7F1ET2XHQfk/hqdefault.jpg",
    "Title": "KATSEYE (캣츠아이) \"PINKY UP\" Official MV",
    "Channel": "HYBE LABELS",
    "Category": "Music",
    "Format": "Standard",
    "Views Gained": 10249738
  },
  {
    "Rank": 23,
    "Change": "-7",
    "Thumbnail": "https://i.ytimg.com/vi/QxXOboCt1LQ/hqdefault.jpg",
    "Title": "Laptop abs flex💀😂 #edit #troll #trollface",
    "Channel": "GigaB Edit",
    "Category": "People & Blogs",
    "Format": "Short",
    "Views Gained": 9470859
  },
  {
    "Rank": 24,
    "Change": "+4",
    "Thumbnail": "https://i.ytimg.com/vi/k_7aeYx32Y0/hqdefault.jpg",
    "Title": "Abew Ketemu Presiden Pak Prabowo #alethaabew",
    "Channel": "Aletha Abew",
    "Category": "Entertainment",
    "Format": "Short",
    "Views Gained": 9179263
  },
  {
    "Rank": 25,
    "Change": "-10",
    "Thumbnail": "https://i.ytimg.com/vi/JyqpIBz6H3w/hqdefault.jpg",
    "Title": "Can The World’s Strongest Man Break Out Of Prison?",
    "Channel": "Topper Guild",
    "Category": "Entertainment",
    "Format": "Short",
    "Views Gained": 9070976
  },
  {
    "Rank": 26,
    "Change": "+3",
    "Thumbnail": "https://i.ytimg.com/vi/j7CvE8yxRVY/hqdefault.jpg",
    "Title": "Mama dan Samir bermain kembang api 🥳 @KLBROBijuRithvik1 #dubbing #remix #trending",
    "Channel": "ALDIS Putra",
    "Category": "Film & Animation",
    "Format": "Short",
    "Views Gained": 8686298
  },
  {
    "Rank": 27,
    "Change": "-1",
    "Thumbnail": "https://i.ytimg.com/vi/pslAyojeDEg/hqdefault.jpg",
    "Title": "Secret giraffe! Perfect camouflage #shorts",
    "Channel": "Miracle Animal Rescues",
    "Category": "Pets & Animals",
    "Format": "Short",
    "Views Gained": 8524461
  },
  {
    "Rank": 28,
    "Change": "+6",
    "Thumbnail": "https://i.ytimg.com/vi/_AH0I6oUx7o/hqdefault.jpg",
    "Title": "Cristiano Ronaldo siiiu 😱👏 #shorts",
    "Channel": "Ronaldo",
    "Category": "People & Blogs",
    "Format": "Short",
    "Views Gained": 8499174
  },
  {
    "Rank": 29,
    "Change": "+2",
    "Thumbnail": "https://i.ytimg.com/vi/S3j0yTwJdMc/hqdefault.jpg",
    "Title": "IBU KAGET, ABANG SALAH MINUM KOPI? | ImehAbang",
    "Channel": "Imeh Abang",
    "Category": "Entertainment",
    "Format": "Short",
    "Views Gained": 7790179
  },
  {
    "Rank": 30,
    "Change": "+9",
    "Thumbnail": "https://i.ytimg.com/vi/uj-PPkHgvw8/hqdefault.jpg",
    "Title": "Ronaldo & Others React to Camera 😂",
    "Channel": "Veltra7",
    "Category": "People & Blogs",
    "Format": "Short",
    "Views Gained": 7569475
  },
  {
    "Rank": 31,
    "Change": "-4",
    "Thumbnail": "https://i.ytimg.com/vi/f6Rq9nY08rg/hqdefault.jpg",
    "Title": "7 Cara Memanggil Daddy #english #learnenglish #bahasainggris",
    "Channel": "Nathan Suparman",
    "Category": "Travel & Events",
    "Format": "Short",
    "Views Gained": 7445768
  },
  {
    "Rank": 32,
    "Change": "+3",
    "Thumbnail": "https://i.ytimg.com/vi/2_jlCfMqfnE/hqdefault.jpg",
    "Title": "SAMPE NGAMBEK😱SYIFA MAU TAMPIL DIDEPAN RIBUAN ORANG TAPI ADAM GAK PEDULI❗️",
    "Channel": "Adam Hidayat",
    "Category": "People & Blogs",
    "Format": "Short",
    "Views Gained": 7129861
  },
  {
    "Rank": 33,
    "Change": "New",
    "Thumbnail": "https://i.ytimg.com/vi/Am2Sy3CpZQw/hqdefault.jpg",
    "Title": "Pail jbl speaker test",
    "Channel": "Lgsuperzone.7",
    "Category": "People & Blogs",
    "Format": "Short",
    "Views Gained": 6380945
  },
  {
    "Rank": 34,
    "Change": "+2",
    "Thumbnail": "https://i.ytimg.com/vi/zkY61VjdfDE/hqdefault.jpg",
    "Title": "Gak suk4 strawberry ‼️ #ytshorts",
    "Channel": "Sakala adiyaka",
    "Category": "People & Blogs",
    "Format": "Short",
    "Views Gained": 6364006
  },
  {
    "Rank": 35,
    "Change": "New",
    "Thumbnail": "https://i.ytimg.com/vi/joEkmFX63_0/hqdefault.jpg",
    "Title": "Pasajero / fake 😂",
    "Channel": "Hablame pri ",
    "Category": "Comedy",
    "Format": "Short",
    "Views Gained": 6198861
  },
  {
    "Rank": 36,
    "Change": "-12",
    "Thumbnail": "https://i.ytimg.com/vi/rg2H0R_SZHE/hqdefault.jpg",
    "Title": "Joselu VS Mbappe VS Lewandowski VS De Jong VS Messi VS Ronaldo",
    "Channel": "Football King",
    "Category": "People & Blogs",
    "Format": "Short",
    "Views Gained": 6058777
  },
  {
    "Rank": 37,
    "Change": "+3",
    "Thumbnail": "https://i.ytimg.com/vi/dKmPEhJ4wjY/hqdefault.jpg",
    "Title": "Anyma, LISA - Bad Angel (Official Music Video)",
    "Channel": "Anyma",
    "Category": "Music",
    "Format": "Standard",
    "Views Gained": 6013079
  },
  {
    "Rank": 38,
    "Change": "-8",
    "Thumbnail": "https://i.ytimg.com/vi/O2JnDgDmQRc/hqdefault.jpg",
    "Title": "花絮，成品在最后 ~~~#滑板教学 #满级小孩 #搞笑 #skate #skateboarding #skateboard #搞笑视频 #极限运动 #滑板男孩 #滑板 #周泽延",
    "Channel": "滑板周泽延",
    "Category": "People & Blogs",
    "Format": "Short",
    "Views Gained": 5956831
  },
  {
    "Rank": 39,
    "Change": "-2",
    "Thumbnail": "https://i.ytimg.com/vi/dSq0Z5XpoLc/hqdefault.jpg",
    "Title": "Pertemuan Bersejarah dr. Tirta dan dr. Gia",
    "Channel": "Raditya Dika",
    "Category": "People & Blogs",
    "Format": "Long",
    "Views Gained": 5749557
  },
  {
    "Rank": 40,
    "Change": "New",
    "Thumbnail": "https://i.ytimg.com/vi/kg8k6fpmHdE/hqdefault.jpg",
    "Title": "How Haaland actually cut that apple 🍎 #football #challenge #haaland",
    "Channel": "Mischief time",
    "Category": "Entertainment",
    "Format": "Short",
    "Views Gained": 5700291
  },
  {
    "Rank": 41,
    "Change": "+5",
    "Thumbnail": "https://i.ytimg.com/vi/3c_WBJWKUNs/hqdefault.jpg",
    "Title": "BURUNG KECEPIT #mamangomel #reality #vlog",
    "Channel": "Mama Ngomel",
    "Category": "People & Blogs",
    "Format": "Short",
    "Views Gained": 5214893
  },
  {
    "Rank": 42,
    "Change": "-1",
    "Thumbnail": "https://i.ytimg.com/vi/oDyu6dC097U/hqdefault.jpg",
    "Title": "Licin banget akal nye kayak minyak 😂",
    "Channel": "Jomblo Family",
    "Category": "Entertainment",
    "Format": "Standard",
    "Views Gained": 5186467
  },
  {
    "Rank": 43,
    "Change": "0",
    "Thumbnail": "https://i.ytimg.com/vi/qjT1CqqvVSA/hqdefault.jpg",
    "Title": "Feisty lady 🤣🤣🤣",
    "Channel": "Lành Lyly",
    "Category": "People & Blogs",
    "Format": "Short",
    "Views Gained": 5106484
  },
  {
    "Rank": 44,
    "Change": "New",
    "Thumbnail": "https://i.ytimg.com/vi/g-nung15iyk/hqdefault.jpg",
    "Title": "Makan kue ulang tahun",
    "Channel": "syahruee",
    "Category": "People & Blogs",
    "Format": "Short",
    "Views Gained": 5063654
  },
  {
    "Rank": 45,
    "Change": "-12",
    "Thumbnail": "https://i.ytimg.com/vi/QBb6OLYV08s/hqdefault.jpg",
    "Title": "MENYESAL NYURUH BOCIL-BOCIL INI #airgambut #premanlontong #premanbarbar #kontenhiburan #ngakak",
    "Channel": "Air Gambut",
    "Category": "People & Blogs",
    "Format": "Short",
    "Views Gained": 4813159
  },
  {
    "Rank": 46,
    "Change": "+4",
    "Thumbnail": "https://i.ytimg.com/vi/6z7fbD8WCYk/hqdefault.jpg",
    "Title": "JEMBATAN CANGAR!",
    "Channel": "TerkaJalanCerita",
    "Category": "Entertainment",
    "Format": "Short",
    "Views Gained": 4763649
  },
  {
    "Rank": 47,
    "Change": "New",
    "Thumbnail": "https://i.ytimg.com/vi/PMd1at7OwiE/hqdefault.jpg",
    "Title": "The Devil Wears Prada 2 | Final Trailer",
    "Channel": "20th Century Studios",
    "Category": "Film & Animation",
    "Format": "Short",
    "Views Gained": 4570040
  },
  {
    "Rank": 48,
    "Change": "-10",
    "Thumbnail": "https://i.ytimg.com/vi/mtlqqmXWe-4/hqdefault.jpg",
    "Title": "Inilah Trik Tukang Cat Lapangan Biar Nggak Pernah Kejebak!",
    "Channel": "Jhelo",
    "Category": "Entertainment",
    "Format": "Short",
    "Views Gained": 4540870
  },
  {
    "Rank": 49,
    "Change": "New",
    "Thumbnail": "https://i.ytimg.com/vi/ooGPjczwr1s/hqdefault.jpg",
    "Title": "JBL Go Essential puliya throw water drop testing",
    "Channel": "Crazybasstest",
    "Category": "People & Blogs",
    "Format": "Short",
    "Views Gained": 4379717
  },
  {
    "Rank": 50,
    "Change": "New",
    "Thumbnail": "https://i.ytimg.com/vi/BwYRQc_4Bdw/hqdefault.jpg",
    "Title": "Katy Perry - The One That Got Away (Lyrics)",
    "Channel": "Vibe Music",
    "Category": "Music",
    "Format": "Standard",
    "Views Gained": 4251452
  }
]