[
  {
    "Rank": 1,
    "Change": "0",
    "Thumbnail": "https://i.ytimg.com/vi/FXMY27T5Mu0/hqdefault.jpg",
    "Title": "I wasn’t expecting the whole village to be on the adventure #funny #shorts #fyp #foryou #fypシ",
    "Channel": "Matt Sowards",
    "Format": "Short",
    "Views Gained": 4122062
  },
  {
    "Rank": 2,
    "Change": "New",
    "Thumbnail": "https://i.ytimg.com/vi/1p-CKmdDFb0/hqdefault.jpg",
    "Title": "Insaan kabhi bhi kisi ke kaam aa sakta hai 🥹",
    "Channel": "Vijay Kumar Viner Vlogs",
    "Format": "Short",
    "Views Gained": 2534817
  },
  {
    "Rank": 3,
    "Change": "+2",
    "Thumbnail": "https://i.ytimg.com/vi/ml_yo2h7gYE/hqdefault.jpg",
    "Title": "Cuando no tienes a Cristiano Ronaldo",
    "Channel": "YargilRed",
    "Format": "Short",
    "Views Gained": 1430816
  },
  {
    "Rank": 4,
    "Change": "New",
    "Thumbnail": "https://i.ytimg.com/vi/mIVRNwa5ue4/hqdefault.jpg",
    "Title": "투우 경기 재밌네",
    "Channel": "황당맨",
    "Format": "Short",
    "Views Gained": 1322498
  },
  {
    "Rank": 5,
    "Change": "-2",
    "Thumbnail": "https://i.ytimg.com/vi/lEP6usEcJGY/hqdefault.jpg",
    "Title": "Justice for him !  #tmkoc #funny #jethalal #daya #shortsfeed #comedy",
    "Channel": "Taarak Mehta Ka Ooltah Chashmah",
    "Format": "Short",
    "Views Gained": 1196610
  },
  {
    "Rank": 6,
    "Change": "+5",
    "Thumbnail": "https://i.ytimg.com/vi/37rloxaz9y0/hqdefault.jpg",
    "Title": "Cuándo juega Colombia vs Mexico",
    "Channel": "YargilRed",
    "Format": "Short",
    "Views Gained": 963164
  },
  {
    "Rank": 7,
    "Change": "-3",
    "Thumbnail": "https://i.ytimg.com/vi/Xp4q3FhOe2E/hqdefault.jpg",
    "Title": "Бригада мастеров качественно выполнит...",
    "Channel": "Какбы Юмор",
    "Format": "Short",
    "Views Gained": 914941
  },
  {
    "Rank": 8,
    "Change": "+1",
    "Thumbnail": "https://i.ytimg.com/vi/K-Gzk-mp7h4/hqdefault.jpg",
    "Title": "Had to fire up the ol’ b*tch detector 🎯🤣 #standup #comedy #amirk #heckler #crowdwork",
    "Channel": "amircomedy",
    "Format": "Short",
    "Views Gained": 888191
  },
  {
    "Rank": 9,
    "Change": "-7",
    "Thumbnail": "https://i.ytimg.com/vi/lXWhl3zyrGA/hqdefault.jpg",
    "Title": "Teeth white kar diye 😂🔥| Indian family #shorts #indian #chaman #relatable #chotabhai #bachpan",
    "Channel": "We r Loser",
    "Format": "Short",
    "Views Gained": 882290
  },
  {
    "Rank": 10,
    "Change": "New",
    "Thumbnail": "https://i.ytimg.com/vi/FbrY8S5Cijc/hqdefault.jpg",
    "Title": "『バイト先に不倫中の先生』#本日も絶体絶命 #ショートコント",
    "Channel": "本日も絶体絶命。",
    "Format": "Short",
    "Views Gained": 831682
  },
  {
    "Rank": 11,
    "Change": "New",
    "Thumbnail": "https://i.ytimg.com/vi/xsioTL3zqqM/hqdefault.jpg",
    "Title": "Isengin bu cika lagi",
    "Channel": "Adliyy_Official",
    "Format": "Short",
    "Views Gained": 776088
  },
  {
    "Rank": 12,
    "Change": "New",
    "Thumbnail": "https://i.ytimg.com/vi/Yt4f41NeWPw/hqdefault.jpg",
    "Title": "o passinho do jamais 🤣🤣🤣",
    "Channel": "Vitor Orth",
    "Format": "Short",
    "Views Gained": 773781
  },
  {
    "Rank": 13,
    "Change": "New",
    "Thumbnail": "https://i.ytimg.com/vi/JkZxkmWIIqA/hqdefault.jpg",
    "Title": "Русские песни",
    "Channel": "Официальный канал КВН",
    "Format": "Short",
    "Views Gained": 726270
  },
  {
    "Rank": 14,
    "Change": "-4",
    "Thumbnail": "https://i.ytimg.com/vi/BLje10nhKnU/hqdefault.jpg",
    "Title": "POV - Seu primo pegou suas Figurinhas 😤 #humor #pov #shorts",
    "Channel": "Biel GEN TV",
    "Format": "Short",
    "Views Gained": 704428
  },
  {
    "Rank": 15,
    "Change": "+2",
    "Thumbnail": "https://i.ytimg.com/vi/2NepWk4fEvY/hqdefault.jpg",
    "Title": "Como a fofoca se espalha na escola 😂",
    "Channel": "Elias Cavalieri ",
    "Format": "Short",
    "Views Gained": 664425
  },
  {
    "Rank": 16,
    "Change": "New",
    "Thumbnail": "https://i.ytimg.com/vi/bJ29f6FpTYo/hqdefault.jpg",
    "Title": "POV VENDEDORES😂 #memes #engraçado #humor #memesbr",
    "Channel": "Kzudo",
    "Format": "Short",
    "Views Gained": 623132
  },
  {
    "Rank": 17,
    "Change": "+2",
    "Thumbnail": "https://i.ytimg.com/vi/5O82HAHTM0s/hqdefault.jpg",
    "Title": "COCA COLA COM AÇÚCAR",
    "Channel": "Dimily",
    "Format": "Short",
    "Views Gained": 595949
  },
  {
    "Rank": 18,
    "Change": "New",
    "Thumbnail": "https://i.ytimg.com/vi/7oyfpaYyd_k/hqdefault.jpg",
    "Title": "最悪のピッチ状態で大逆転を生んだゴールキーパー",
    "Channel": "1分動画",
    "Format": "Short",
    "Views Gained": 594237
  },
  {
    "Rank": 19,
    "Change": "-4",
    "Thumbnail": "https://i.ytimg.com/vi/z8a46AT7k-Q/hqdefault.jpg",
    "Title": "장사의 신이 극찬한 손님에게 진심인 사장님",
    "Channel": "클립덕",
    "Format": "Short",
    "Views Gained": 508626
  },
  {
    "Rank": 20,
    "Change": "-7",
    "Thumbnail": "https://i.ytimg.com/vi/lKHzCLw0brc/hqdefault.jpg",
    "Title": "Gerakan ibadah Bocil DS di Banten #anakdesa #minivlog #comedy #sholat #banten",
    "Channel": "Warga DS",
    "Format": "Short",
    "Views Gained": 480139
  },
  {
    "Rank": 21,
    "Change": "+6",
    "Thumbnail": "https://i.ytimg.com/vi/f5XjixW8FVY/hqdefault.jpg",
    "Title": "Tillu Inside Blue Drum🛢️🤣#shorts #comedy #funny #olidavines",
    "Channel": "OLIDA  Vlogs and Vines",
    "Format": "Short",
    "Views Gained": 458743
  },
  {
    "Rank": 22,
    "Change": "-15",
    "Thumbnail": "https://i.ytimg.com/vi/btxeUFVtSzI/hqdefault.jpg",
    "Title": "That kid was from the future 🥶🫣",
    "Channel": "THTOM",
    "Format": "Short",
    "Views Gained": 450888
  },
  {
    "Rank": 23,
    "Change": "New",
    "Thumbnail": "https://i.ytimg.com/vi/MCCVt8IhJkA/hqdefault.jpg",
    "Title": "Count Binface destroys Sky News interviewer",
    "Channel": "Count Binface",
    "Format": "Standard",
    "Views Gained": 422748
  },
  {
    "Rank": 24,
    "Change": "-2",
    "Thumbnail": "https://i.ytimg.com/vi/3_43-8nYGFo/hqdefault.jpg",
    "Title": "Rumah kucing untuk si Oyen 🤗 #relate #videolucu #komedi #funnyvideo #funnycat #kucing #kucinglucu",
    "Channel": "Salasati Hunafa ",
    "Format": "Short",
    "Views Gained": 421838
  },
  {
    "Rank": 25,
    "Change": "New",
    "Thumbnail": "https://i.ytimg.com/vi/EDAPwYHiOc4/hqdefault.jpg",
    "Title": "【伝説ダジャレ】3億人中13人は爆笑する【2ch面白いスレ】",
    "Channel": "ロンロンの天秤ニカケルch",
    "Format": "Short",
    "Views Gained": 420844
  },
  {
    "Rank": 26,
    "Change": "New",
    "Thumbnail": "https://i.ytimg.com/vi/DWIhScr3L6M/hqdefault.jpg",
    "Title": "Que triste el partido de Corea contra México",
    "Channel": "Comicoreano",
    "Format": "Short",
    "Views Gained": 417326
  },
  {
    "Rank": 27,
    "Change": "-11",
    "Thumbnail": "https://i.ytimg.com/vi/9mqv3mFmmOg/hqdefault.jpg",
    "Title": "Domicilio perdido 😂",
    "Channel": "Hablame pri ",
    "Format": "Short",
    "Views Gained": 417239
  },
  {
    "Rank": 28,
    "Change": "New",
    "Thumbnail": "https://i.ytimg.com/vi/0M9yRpzR85U/hqdefault.jpg",
    "Title": "Matt Damon Surprise Attacks Kimmel AGAIN & Trump’s Dummy of a Deal with Iran Faces Backlash",
    "Channel": "Jimmy Kimmel Live",
    "Format": "Standard",
    "Views Gained": 405472
  },
  {
    "Rank": 29,
    "Change": "-15",
    "Thumbnail": "https://i.ytimg.com/vi/LZMCdIZqDC8/hqdefault.jpg",
    "Title": "Trump’s Childish Behavior with World Leaders, Republicans Bash His Iran Deal & Guillermo’s Huge News",
    "Channel": "Jimmy Kimmel Live",
    "Format": "Standard",
    "Views Gained": 399619
  },
  {
    "Rank": 30,
    "Change": "New",
    "Thumbnail": "https://i.ytimg.com/vi/64CDFdE0PgA/hqdefault.jpg",
    "Title": "He Said No 😂 Dave Chappelle",
    "Channel": "Hoovers View",
    "Format": "Standard",
    "Views Gained": 391599
  },
  {
    "Rank": 31,
    "Change": "New",
    "Thumbnail": "https://i.ytimg.com/vi/VaeALofc2Cw/hqdefault.jpg",
    "Title": "Подставила подругу 😮 #тнт #юмор #смех #овр #овршоу #флирт #отношения #ресторан #Федункив #Шаляпин",
    "Channel": "ОВР Шоу",
    "Format": "Short",
    "Views Gained": 382352
  },
  {
    "Rank": 32,
    "Change": "-14",
    "Thumbnail": "https://i.ytimg.com/vi/9786g_MpzqM/hqdefault.jpg",
    "Title": "Kid knows how to get a FREE upgrade to business class on a plane",
    "Channel": "Jeenie.Weenie",
    "Format": "Short",
    "Views Gained": 372938
  },
  {
    "Rank": 33,
    "Change": "New",
    "Thumbnail": "https://i.ytimg.com/vi/jvijD0EZ_N4/hqdefault.jpg",
    "Title": "Who did I miss? #heatwave #schoollife #teachers #students",
    "Channel": "Teacher Tommy T",
    "Format": "Short",
    "Views Gained": 365314
  },
  {
    "Rank": 34,
    "Change": "-14",
    "Thumbnail": "https://i.ytimg.com/vi/uuk0-LMB75I/hqdefault.jpg",
    "Title": "Он ждал этот момент несколько дней и наконец решился #shorts",
    "Channel": "Гохисыч",
    "Format": "Short",
    "Views Gained": 357345
  },
  {
    "Rank": 35,
    "Change": "-11",
    "Thumbnail": "https://i.ytimg.com/vi/xwjuW5fr5x4/hqdefault.jpg",
    "Title": "O quartel ganhou novas recrutas 😂😭🤦 KKKKKKK #shorts #engraçado #humor #comedia",
    "Channel": "Tio Q Rir",
    "Format": "Short",
    "Views Gained": 329740
  },
  {
    "Rank": 36,
    "Change": "New",
    "Thumbnail": "https://i.ytimg.com/vi/fFMFtmoVnKs/hqdefault.jpg",
    "Title": "Das Gut genug Battle.",
    "Channel": "Alaeddin.official",
    "Format": "Short",
    "Views Gained": 321331
  },
  {
    "Rank": 37,
    "Change": "New",
    "Thumbnail": "https://i.ytimg.com/vi/-xDaxULa_Rk/hqdefault.jpg",
    "Title": "Wondering if Bob's available for any trims during this World Cup... Asking for a friend 😆",
    "Channel": "Would I Lie To You?",
    "Format": "Standard",
    "Views Gained": 307178
  },
  {
    "Rank": 38,
    "Change": "-12",
    "Thumbnail": "https://i.ytimg.com/vi/q1SJ-g-cK74/hqdefault.jpg",
    "Title": "ЗАСМЕЯЛСЯ-ПОДПИСАЛСЯ! Ч.232😂ОЧЕНЬ СМЕШНО!",
    "Channel": "Мужики Шортс",
    "Format": "Short",
    "Views Gained": 300341
  },
  {
    "Rank": 39,
    "Change": "-27",
    "Thumbnail": "https://i.ytimg.com/vi/f8DsyyY5bTI/hqdefault.jpg",
    "Title": "kita kaya Paak",
    "Channel": "Komedi true ",
    "Format": "Short",
    "Views Gained": 272111
  },
  {
    "Rank": 40,
    "Change": "-4",
    "Thumbnail": "https://i.ytimg.com/vi/lGUfnE3nQAg/hqdefault.jpg",
    "Title": "Wait for twist 🤣🔥 #mabucrush",
    "Channel": "Mabu Crush",
    "Format": "Short",
    "Views Gained": 247058
  },
  {
    "Rank": 41,
    "Change": "New",
    "Thumbnail": "https://i.ytimg.com/vi/fVg3Cm6MEys/hqdefault.jpg",
    "Title": "Trump Deal Lets Iran Keep Missile Arsenal and $400 Billion & Republicans Lash Out | The Daily Show",
    "Channel": "The Daily Show",
    "Format": "Standard",
    "Views Gained": 241610
  },
  {
    "Rank": 42,
    "Change": "New",
    "Thumbnail": "https://i.ytimg.com/vi/zWMRr-cTQNg/hqdefault.jpg",
    "Title": "Trump Faces GOP Fury Over Iran Deal; Fox News Blames JD Vance; Iran Gets $300 Billion: A Closer Look",
    "Channel": "Late Night with Seth Meyers",
    "Format": "Standard",
    "Views Gained": 234210
  },
  {
    "Rank": 43,
    "Change": "+2",
    "Thumbnail": "https://i.ytimg.com/vi/bugWUFWuduU/hqdefault.jpg",
    "Title": "On est prêts mais pas elles ! 😅😂 #family #humour #fun",
    "Channel": "familleenxl",
    "Format": "Short",
    "Views Gained": 223965
  },
  {
    "Rank": 44,
    "Change": "-3",
    "Thumbnail": "https://i.ytimg.com/vi/TC3dTMGaXSE/hqdefault.jpg",
    "Title": "A ideia não era boa? 😭",
    "Channel": "Paulinho",
    "Format": "Short",
    "Views Gained": 221695
  },
  {
    "Rank": 45,
    "Change": "-11",
    "Thumbnail": "https://i.ytimg.com/vi/Y-MNRkdiVYY/hqdefault.jpg",
    "Title": "Татуировщик такого явно не ожидал",
    "Channel": "Дион ",
    "Format": "Short",
    "Views Gained": 215948
  },
  {
    "Rank": 46,
    "Change": "-16",
    "Thumbnail": "https://i.ytimg.com/vi/Xu2BGiX-KLc/hqdefault.jpg",
    "Title": "Would you take the blame or snitch on your dad?💀 #comedy",
    "Channel": "marrkadams",
    "Format": "Short",
    "Views Gained": 201592
  },
  {
    "Rank": 47,
    "Change": "New",
    "Thumbnail": "https://i.ytimg.com/vi/64NL5jfM5A4/hqdefault.jpg",
    "Title": "Taktik bola paling mematikan di dunia  #memeindonesia #memes #memengakakkocak #ngakak",
    "Channel": "MR.MEMEZZZSSS",
    "Format": "Short",
    "Views Gained": 201048
  },
  {
    "Rank": 48,
    "Change": "-6",
    "Thumbnail": "https://i.ytimg.com/vi/N7Azxdy3Jsw/hqdefault.jpg",
    "Title": "Не берут в ад 🤣 #тнт #юмор #смех #comedyclub #камедиклаб #миниатюра #овр #Харламов #Дорохов",
    "Channel": "Comedy Club",
    "Format": "Short",
    "Views Gained": 192633
  },
  {
    "Rank": 49,
    "Change": "New",
    "Thumbnail": "https://i.ytimg.com/vi/OI1DrApZ0qk/hqdefault.jpg",
    "Title": "Quand ta pote te couvre pour aller rejoindre ton crush #humour #pourtoi #foryou",
    "Channel": "Shayvise",
    "Format": "Short",
    "Views Gained": 188242
  },
  {
    "Rank": 50,
    "Change": "-15",
    "Thumbnail": "https://i.ytimg.com/vi/QPry7u_F8Lk/hqdefault.jpg",
    "Title": "КЛЕЩ (смешное видео, юмор, приколы, поржать, прикол, смех)",
    "Channel": "Натурал Альбертович",
    "Format": "Short",
    "Views Gained": 187114
  }
]