[
  {
    "Rank": 1,
    "Change": "0",
    "Thumbnail": "https://i.ytimg.com/vi/d81YM8ysDww/hqdefault.jpg",
    "Title": "Gave gifts to classmates",
    "Channel": "dednahype",
    "Category": "Comedy",
    "Format": "Short",
    "Views Gained": 50345238
  },
  {
    "Rank": 2,
    "Change": "+2",
    "Thumbnail": "https://i.ytimg.com/vi/h2kh_vSAgXQ/hqdefault.jpg",
    "Title": "Banku Bhaiya BTS with Result😂🔥  #prashulovers #prasvcreation #layekfam #prashantrajput #funny",
    "Channel": "Prashant Rajput",
    "Category": "Entertainment",
    "Format": "Short",
    "Views Gained": 36648035
  },
  {
    "Rank": 3,
    "Change": "-1",
    "Thumbnail": "https://i.ytimg.com/vi/RB71Z-vVvCc/hqdefault.jpg",
    "Title": "Find The Real Celebrity, Win $10,000",
    "Channel": "MrBeast",
    "Category": "Entertainment",
    "Format": "Short",
    "Views Gained": 33654010
  },
  {
    "Rank": 4,
    "Change": "-1",
    "Thumbnail": "https://i.ytimg.com/vi/mjRh7Mxq7D4/hqdefault.jpg",
    "Title": "Sabko mila gift 🎁🥰 #shorts #funny",
    "Channel": "Uma Bai",
    "Category": "People & Blogs",
    "Format": "Short",
    "Views Gained": 25241145
  },
  {
    "Rank": 5,
    "Change": "0",
    "Thumbnail": "https://i.ytimg.com/vi/YyepU5ztLf4/hqdefault.jpg",
    "Title": "Shararat | Dhurandhar | Ranveer, Aditya Dhar, Shashwat, Jasmine, Madhubanti, Ayesha, Krystle",
    "Channel": "Saregama Music",
    "Category": "Music",
    "Format": "Standard",
    "Views Gained": 24632342
  },
  {
    "Rank": 6,
    "Change": "0",
    "Thumbnail": "https://i.ytimg.com/vi/SxWjiROJ9Io/hqdefault.jpg",
    "Title": "Christmas pe santa🎅 #funny #comedy #comedyvideo #christmas",
    "Channel": "Ketan mehta",
    "Category": "People & Blogs",
    "Format": "Short",
    "Views Gained": 24049732
  },
  {
    "Rank": 7,
    "Change": "0",
    "Thumbnail": "https://i.ytimg.com/vi/Mzw2ttJD2qQ/hqdefault.jpg",
    "Title": "The Odyssey | Official Trailer",
    "Channel": "Universal Pictures",
    "Category": "Entertainment",
    "Format": "Short",
    "Views Gained": 19835679
  },
  {
    "Rank": 8,
    "Change": "+1",
    "Thumbnail": "https://i.ytimg.com/vi/H7vHmNX0Koc/hqdefault.jpg",
    "Title": "Finally ye cute trend bana hi liya 😂🫶🏻 #priyalkukreja #shorts #ytshorts",
    "Channel": "Priyal Kukreja",
    "Category": "People & Blogs",
    "Format": "Short",
    "Views Gained": 13866436
  },
  {
    "Rank": 9,
    "Change": "+3",
    "Thumbnail": "https://i.ytimg.com/vi/Xj149TFKhjM/hqdefault.jpg",
    "Title": "I Raced Rumi?",
    "Channel": "Zhong",
    "Category": "Entertainment",
    "Format": "Short",
    "Views Gained": 11882683
  },
  {
    "Rank": 10,
    "Change": "+3",
    "Thumbnail": "https://i.ytimg.com/vi/nWiekcpbiCU/hqdefault.jpg",
    "Title": "Tillu gets an ORANGE🍊😂#shorts #comedy #funny #olidavines",
    "Channel": "OLIDA  Vlogs and Vines",
    "Category": "Comedy",
    "Format": "Short",
    "Views Gained": 9846202
  },
  {
    "Rank": 11,
    "Change": "+4",
    "Thumbnail": "https://i.ytimg.com/vi/OXOYXtFnJ7U/hqdefault.jpg",
    "Title": "Building Wooden Log Cabin in Forest 🌲🥰 Survival House Step by Step",
    "Channel": "nikhlu007",
    "Category": "Comedy",
    "Format": "Short",
    "Views Gained": 9745005
  },
  {
    "Rank": 12,
    "Change": "+2",
    "Thumbnail": "https://i.ytimg.com/vi/nZwrhOK1p78/hqdefault.jpg",
    "Title": "iPhone 17 Pro | A19 Pro Chip | Peak Performance | Apple",
    "Channel": "Apple India",
    "Category": "Science & Technology",
    "Format": "Short",
    "Views Gained": 9606065
  },
  {
    "Rank": 13,
    "Change": "New",
    "Thumbnail": "https://i.ytimg.com/vi/fDvVCS17P5A/hqdefault.jpg",
    "Title": "Jana Nayagan – Chella Magale Lyrical | Thalapathy Vijay | Pooja Hegde | H Vinoth | Anirudh | KVN",
    "Channel": "T-Series",
    "Category": "Music",
    "Format": "Standard",
    "Views Gained": 9596416
  },
  {
    "Rank": 14,
    "Change": "+3",
    "Thumbnail": "https://i.ytimg.com/vi/lcw4TDMBjZA/hqdefault.jpg",
    "Title": "AADAT (Official Video): YO YO HONEY SINGH | AP DHILLON | VAANI KAPOOR | 51 GLORIOUS DAYS | BHUSHAN K",
    "Channel": "T-Series",
    "Category": "Music",
    "Format": "Standard",
    "Views Gained": 9149147
  },
  {
    "Rank": 15,
    "Change": "-7",
    "Thumbnail": "https://i.ytimg.com/vi/eReS_sVR7f8/hqdefault.jpg",
    "Title": "अम्मा की खामोशी कोई नहीं समझता आज कितनी ठंड थी #trending #younickviral #viral #trend #humanity",
    "Channel": "YouNick Viral Vlogs",
    "Category": "People & Blogs",
    "Format": "Short",
    "Views Gained": 8926131
  },
  {
    "Rank": 16,
    "Change": "+14",
    "Thumbnail": "https://i.ytimg.com/vi/YG-lhRi7ihM/hqdefault.jpg",
    "Title": "Struggle 🔥",
    "Channel": "up wala aryan",
    "Category": "Gaming",
    "Format": "Short",
    "Views Gained": 8792497
  },
  {
    "Rank": 17,
    "Change": "+4",
    "Thumbnail": "https://i.ytimg.com/vi/slL5ZHgaubg/hqdefault.jpg",
    "Title": "The Best Tool For Exam #shorts",
    "Channel": "VENDY YADUWANSHI",
    "Category": "Entertainment",
    "Format": "Short",
    "Views Gained": 8257737
  },
  {
    "Rank": 18,
    "Change": "-2",
    "Thumbnail": "https://i.ytimg.com/vi/dMqxc9jU3io/hqdefault.jpg",
    "Title": "रोहित मेहरा की जादुई Electric Cycle 🔋⚡🚲#shorts",
    "Channel": "Tech Master Shorts",
    "Category": "Science & Technology",
    "Format": "Short",
    "Views Gained": 8130226
  },
  {
    "Rank": 19,
    "Change": "New",
    "Thumbnail": "https://i.ytimg.com/vi/oNGUzoWK6a4/hqdefault.jpg",
    "Title": "Ye Wish Kya Puri Ho Payegi ? 😱 #shorts #ytshorts #santaclaus #christmas",
    "Channel": "Nishu jeet aarya",
    "Category": "People & Blogs",
    "Format": "Short",
    "Views Gained": 8110381
  },
  {
    "Rank": 20,
    "Change": "-1",
    "Thumbnail": "https://i.ytimg.com/vi/wWIJNCU8OOs/hqdefault.jpg",
    "Title": "Reality of Dhurandhar Film | Dhruv Rathee",
    "Channel": "Dhruv Rathee",
    "Category": "Education",
    "Format": "Long",
    "Views Gained": 8037416
  },
  {
    "Rank": 21,
    "Change": "-10",
    "Thumbnail": "https://i.ytimg.com/vi/uD3SDbdH-vg/hqdefault.jpg",
    "Title": "chiku ne Manu ko Dra Diya 😱 #shorts #funny #vlog",
    "Channel": "SANSAR COMEDY BAR",
    "Category": "Comedy",
    "Format": "Short",
    "Views Gained": 8013571
  },
  {
    "Rank": 22,
    "Change": "-2",
    "Thumbnail": "https://i.ytimg.com/vi/Qhwafoo7Pnc/hqdefault.jpg",
    "Title": "Aawaara Angaara (Full Video): Tere Ishk Mein | Dhanush, Kriti | AR Rahman,Faheem|Aanand LR|Bhushan K",
    "Channel": "T-Series",
    "Category": "Music",
    "Format": "Standard",
    "Views Gained": 7504274
  },
  {
    "Rank": 23,
    "Change": "0",
    "Thumbnail": "https://i.ytimg.com/vi/jf8LduX6-dU/hqdefault.jpg",
    "Title": "Yaaru seekirama sapdaringalo avanga thatta eduthu vainga.. #soundsettai #comedy #funny #villagelife",
    "Channel": "Sound Settai",
    "Category": "People & Blogs",
    "Format": "Short",
    "Views Gained": 7261181
  },
  {
    "Rank": 24,
    "Change": "0",
    "Thumbnail": "https://i.ytimg.com/vi/jmcLUKkHgKA/hqdefault.jpg",
    "Title": "Middle Class 💔😱 Wait For End 💸🙏🏻 #shorts #maa #school",
    "Channel": "Jomy Production",
    "Category": "Entertainment",
    "Format": "Short",
    "Views Gained": 6442166
  },
  {
    "Rank": 25,
    "Change": "-15",
    "Thumbnail": "https://i.ytimg.com/vi/VVVP6V9clDA/hqdefault.jpg",
    "Title": "Mummy Ban gyi Bhoot 😂❤️ll Vishal Rajput shorts #celebratewithshorts #vishalsinghrajput #funny",
    "Channel": "Vishal Rajput Official",
    "Category": "Entertainment",
    "Format": "Short",
    "Views Gained": 6361002
  },
  {
    "Rank": 26,
    "Change": "-4",
    "Thumbnail": "https://i.ytimg.com/vi/NP6r1YKmo7g/hqdefault.jpg",
    "Title": "Candy Shop - Tony Kakkar, Neha Kakkar | Official Video",
    "Channel": "Tony Kakkar",
    "Category": "Music",
    "Format": "Standard",
    "Views Gained": 6149957
  },
  {
    "Rank": 27,
    "Change": "+5",
    "Thumbnail": "https://i.ytimg.com/vi/DvbxkId8ys8/hqdefault.jpg",
    "Title": "Damad ji 😭💔🙏 #trending #shorts",
    "Channel": "Its rahil Khan 05",
    "Category": "Film & Animation",
    "Format": "Short",
    "Views Gained": 6011793
  },
  {
    "Rank": 28,
    "Change": "+11",
    "Thumbnail": "https://i.ytimg.com/vi/c1WLdWBkW14/hqdefault.jpg",
    "Title": "Thand me biwi se punga 🤣😂 || brother sister love|| Shubham ||ananya  #trending #youtube #foryou",
    "Channel": "Shubham Yadav",
    "Category": "Entertainment",
    "Format": "Short",
    "Views Gained": 5651523
  },
  {
    "Rank": 29,
    "Change": "0",
    "Thumbnail": "https://i.ytimg.com/vi/tUIWMTQy8oo/hqdefault.jpg",
    "Title": "DRINK BALL 🍸🍹⚾ #shorts #youtubeshorts #cricket #unboxing #ball #funny",
    "Channel": "Box Of Vengeance",
    "Category": "People & Blogs",
    "Format": "Short",
    "Views Gained": 5396172
  },
  {
    "Rank": 30,
    "Change": "+19",
    "Thumbnail": "https://i.ytimg.com/vi/cnKHHxiJE1g/hqdefault.jpg",
    "Title": "😡Ada Paavi 😱 real end twist 🤣 #shorts #trending #funny #comedy #cpsaicharan #viralvideo",
    "Channel": "Cp Saicharan",
    "Category": "Entertainment",
    "Format": "Short",
    "Views Gained": 4982289
  },
  {
    "Rank": 31,
    "Change": "+9",
    "Thumbnail": "https://i.ytimg.com/vi/_Dfc89TY-aA/hqdefault.jpg",
    "Title": "Peaky Blinders: The Immortal Man | Official Teaser | Netflix",
    "Channel": "Netflix",
    "Category": "Entertainment",
    "Format": "Short",
    "Views Gained": 4977113
  },
  {
    "Rank": 32,
    "Change": "New",
    "Thumbnail": "https://i.ytimg.com/vi/YhqMotKOJ7Q/hqdefault.jpg",
    "Title": "New Hoodie Trend Completed 😂 #dushyantkukreja #shorts",
    "Channel": "Dushyant kukreja",
    "Category": "Entertainment",
    "Format": "Short",
    "Views Gained": 4883620
  },
  {
    "Rank": 33,
    "Change": "+9",
    "Thumbnail": "https://i.ytimg.com/vi/XOjwt82bQ0Q/hqdefault.jpg",
    "Title": "#Video | आग लगइबू का | #Khesari Lal Yadav | Aag Lagaibu Ka | #Anupma Yadav | New Bhojpuri Song 2025",
    "Channel": "Trimurti Music World",
    "Category": "Music",
    "Format": "Standard",
    "Views Gained": 4862068
  },
  {
    "Rank": 34,
    "Change": "+3",
    "Thumbnail": "https://i.ytimg.com/vi/9AcEgUlD7Hg/hqdefault.jpg",
    "Title": "Real end twist 😂 wait for last 😂🤣#shorts #trending #funny #viral #viralvideo #youtubeshorts",
    "Channel": "Rishan sriansh & Sree nayana",
    "Category": "Entertainment",
    "Format": "Short",
    "Views Gained": 4848362
  },
  {
    "Rank": 35,
    "Change": "-1",
    "Thumbnail": "https://i.ytimg.com/vi/a10nD5yN0Yw/hqdefault.jpg",
    "Title": "Vijay came in strange world 🤑😱😍 | Vijay saiwal | #shorts #school #vijaysimranshorts #schoollife",
    "Channel": "Vijay Saiwal",
    "Category": "People & Blogs",
    "Format": "Short",
    "Views Gained": 4807416
  },
  {
    "Rank": 36,
    "Change": "-10",
    "Thumbnail": "https://i.ytimg.com/vi/NEAsHXgmqas/hqdefault.jpg",
    "Title": "Peddi Reddy Full Song | Bullet Bandi Laxman | Madeen Sk | Naga Durga | Leading Boys",
    "Channel": "Sound Lagare",
    "Category": "Music",
    "Format": "Standard",
    "Views Gained": 4754916
  },
  {
    "Rank": 37,
    "Change": "-4",
    "Thumbnail": "https://i.ytimg.com/vi/0WFx6v8tvFg/hqdefault.jpg",
    "Title": "#VIDEO | रंगबाज़ | RANGBAAZ | Khesari Lal Yadav, Shilpi Raj | Priyanka Rai | New Bhojpuri Song 2025",
    "Channel": "Khesari Music World",
    "Category": "Music",
    "Format": "Standard",
    "Views Gained": 4692059
  },
  {
    "Rank": 38,
    "Change": "-3",
    "Thumbnail": "https://i.ytimg.com/vi/aT4N7jn2Eww/hqdefault.jpg",
    "Title": "Run Down The City - Monica | Dhurandhar | Ranveer, Sara, Shashwat, Reble, Asha Bhosle, R.D. Burman",
    "Channel": "Saregama Music",
    "Category": "Music",
    "Format": "Standard",
    "Views Gained": 4652030
  },
  {
    "Rank": 39,
    "Change": "New",
    "Thumbnail": "https://i.ytimg.com/vi/Gza6kZvDjnY/hqdefault.jpg",
    "Title": "Riya Ban gyi Bhoot part - 4 ll Vishal Rajput shorts #celebratewithshorts #vishalsinghrajput #comedy",
    "Channel": "Vishal Rajput Official",
    "Category": "Entertainment",
    "Format": "Short",
    "Views Gained": 4608847
  },
  {
    "Rank": 40,
    "Change": "-4",
    "Thumbnail": "https://i.ytimg.com/vi/51B3DbBJy2c/hqdefault.jpg",
    "Title": "Didi ka khauf🤣 #zidaanshahidaly",
    "Channel": "Zidaan Shahid Aly",
    "Category": "People & Blogs",
    "Format": "Short",
    "Views Gained": 4507893
  },
  {
    "Rank": 41,
    "Change": "-16",
    "Thumbnail": "https://i.ytimg.com/vi/ip8o5hDFLhI/hqdefault.jpg",
    "Title": "Jana Nayagan – Oru Pere Varalaaru Lyrical | Thalapathy Vijay | H Vinoth |Anirudh |KVN |Vishal Mishra",
    "Channel": "T-Series",
    "Category": "Music",
    "Format": "Standard",
    "Views Gained": 4506293
  },
  {
    "Rank": 42,
    "Change": "-15",
    "Thumbnail": "https://i.ytimg.com/vi/khgpJwuLYTQ/hqdefault.jpg",
    "Title": "He broke the golf simulator",
    "Channel": "Zach King",
    "Category": "Entertainment",
    "Format": "Short",
    "Views Gained": 4486579
  },
  {
    "Rank": 43,
    "Change": "New",
    "Thumbnail": "https://i.ytimg.com/vi/oukHSTSoPgQ/hqdefault.jpg",
    "Title": "Santa Claus ( Part 3 ) #mastikipaathsala #babu #santaclaus #merrychristmas Christmas",
    "Channel": "Sr indori09",
    "Category": "Entertainment",
    "Format": "Short",
    "Views Gained": 4446195
  },
  {
    "Rank": 44,
    "Change": "+1",
    "Thumbnail": "https://i.ytimg.com/vi/iPCWamt3XME/hqdefault.jpg",
    "Title": "Ekaki Chapter 3 : Invasion | Ashish Chanchlani | ACV Studios",
    "Channel": "ashish chanchlani vines",
    "Category": "Comedy",
    "Format": "Long",
    "Views Gained": 4330298
  },
  {
    "Rank": 45,
    "Change": "-4",
    "Thumbnail": "https://i.ytimg.com/vi/ma_3kbF8vLg/hqdefault.jpg",
    "Title": "Love you papa 🥰 | The most viral emotional video by baapbeta beta 🔥 #ytshorts #shorts",
    "Channel": "up wala aryan",
    "Category": "Gaming",
    "Format": "Short",
    "Views Gained": 4134737
  },
  {
    "Rank": 46,
    "Change": "-15",
    "Thumbnail": "https://i.ytimg.com/vi/b9JZXO5e8IY/hqdefault.jpg",
    "Title": "#VIDEO | #Khesari Lal Yadav | लहंगा में मीटर 2 | #Shilpi Raj | Ft #Raksha Gupta | Bhojpuri Gana 2025",
    "Channel": "West Bhojpuri",
    "Category": "Music",
    "Format": "Standard",
    "Views Gained": 4082770
  },
  {
    "Rank": 47,
    "Change": "New",
    "Thumbnail": "https://i.ytimg.com/vi/2jHjrUXCOWc/hqdefault.jpg",
    "Title": "Anant ki Mumma gyi rope pr chalne",
    "Channel": "PoonamSikarwar",
    "Category": "Entertainment",
    "Format": "Short",
    "Views Gained": 3855157
  },
  {
    "Rank": 48,
    "Change": "New",
    "Thumbnail": "https://i.ytimg.com/vi/KZ8TWnWq6ak/hqdefault.jpg",
    "Title": "Tom 🍓 Jerry (Soumya&Ammu)Real End Twist😍🎈#v5familyshow  #shorts #viralvideo",
    "Channel": "V5 Family Show",
    "Category": "Entertainment",
    "Format": "Short",
    "Views Gained": 3815500
  },
  {
    "Rank": 49,
    "Change": "-31",
    "Thumbnail": "https://i.ytimg.com/vi/YEv0zokK140/hqdefault.jpg",
    "Title": "Happy Patel Khatarnak Jasoos | Official Trailer | Vir Das | Aamir Khan | 16th January 2026",
    "Channel": "Aamir Khan Talkies",
    "Category": "People & Blogs",
    "Format": "Standard",
    "Views Gained": 3757650
  },
  {
    "Rank": 50,
    "Change": "-2",
    "Thumbnail": "https://i.ytimg.com/vi/y1AMRvWw6l4/hqdefault.jpg",
    "Title": "Santa Claus bhi local hai😭😂#funny #comedy #shorts #koushalmonga #merrychristmas",
    "Channel": "Koushal Monga",
    "Category": "Gaming",
    "Format": "Short",
    "Views Gained": 3736251
  }
]