[
  {
    "Rank": 1,
    "Change": "0",
    "Thumbnail": "https://i.ytimg.com/vi/zRtGL0-5rg4/hqdefault.jpg",
    "Title": "Last To Leave Grocery Store, Wins $250,000",
    "Channel": "MrBeast",
    "Category": "Entertainment",
    "Views Gained": 51037899
  },
  {
    "Rank": 2,
    "Change": "New",
    "Thumbnail": "https://i.ytimg.com/vi/Vo6QTBMdUfU/hqdefault.jpg",
    "Title": "1 Day vs 50,000 Day Build Challenge",
    "Channel": "MrBeast Gaming",
    "Category": "Gaming",
    "Views Gained": 9003446
  },
  {
    "Rank": 3,
    "Change": "-1",
    "Thumbnail": "https://i.ytimg.com/vi/QF5YpZI1wnk/hqdefault.jpg",
    "Title": "I Survived 100 Days in Skyblock",
    "Channel": "MrBeast Gaming",
    "Category": "Gaming",
    "Views Gained": 6005563
  },
  {
    "Rank": 4,
    "Change": "-1",
    "Thumbnail": "https://i.ytimg.com/vi/gBFOFzMzNjc/hqdefault.jpg",
    "Title": "My Dad Can't Stop My Secret Sleepover",
    "Channel": "Jordan Matter",
    "Category": "Entertainment",
    "Views Gained": 4754922
  },
  {
    "Rank": 5,
    "Change": "-1",
    "Thumbnail": "https://i.ytimg.com/vi/k9QoSK_G2mw/hqdefault.jpg",
    "Title": "HICE UN CONCURSO DE TALENTOS POR $10.000!",
    "Channel": "Fede Vigevani",
    "Category": "Entertainment",
    "Views Gained": 4229658
  },
  {
    "Rank": 6,
    "Change": "-1",
    "Thumbnail": "https://i.ytimg.com/vi/t3H5DnhQivE/hqdefault.jpg",
    "Title": "20 HOMBRES VS 1 ARTISTA: YERIMUA 🇲🇽",
    "Channel": "lebriah",
    "Category": "Entertainment",
    "Views Gained": 4129027
  },
  {
    "Rank": 7,
    "Change": "+1",
    "Thumbnail": "https://i.ytimg.com/vi/PQ5Id2Gkvkk/hqdefault.jpg",
    "Title": "Yeraltı 12. Bölüm",
    "Channel": "Yeraltı",
    "Category": "Entertainment",
    "Views Gained": 3357270
  },
  {
    "Rank": 8,
    "Change": "New",
    "Thumbnail": "https://i.ytimg.com/vi/JraNFP78WE8/hqdefault.jpg",
    "Title": "Taşacak Bu Deniz 25. Bölüm @trt1",
    "Channel": "Taşacak Bu Deniz",
    "Category": "Entertainment",
    "Views Gained": 2922380
  },
  {
    "Rank": 9,
    "Change": "+5",
    "Thumbnail": "https://i.ytimg.com/vi/kGOMBv8tbPw/hqdefault.jpg",
    "Title": "Le Pire Stagiaire : moniteur d'auto-école (version longue)",
    "Channel": "Greg Guillotin",
    "Category": "Comedy",
    "Views Gained": 2849907
  },
  {
    "Rank": 10,
    "Change": "New",
    "Thumbnail": "https://i.ytimg.com/vi/Y2JzBV3Epl4/hqdefault.jpg",
    "Title": "My Daughter Survives 6 Schools That Shouldn’t Exist",
    "Channel": "Jordan Matter",
    "Category": "Entertainment",
    "Views Gained": 2800551
  },
  {
    "Rank": 11,
    "Change": "-4",
    "Thumbnail": "https://i.ytimg.com/vi/bFcu2-3GET8/hqdefault.jpg",
    "Title": "Delikanlı 3. Bölüm",
    "Channel": "Delikanlı",
    "Category": "Entertainment",
    "Views Gained": 2750243
  },
  {
    "Rank": 12,
    "Change": "-3",
    "Thumbnail": "https://i.ytimg.com/vi/hzHvU6agizo/hqdefault.jpg",
    "Title": "BEFORE GRADUATION -  OMECHE OKO, JOSEPHINE SUNDAY(JOJO), CHIDIMMA UGWU latest 2026 nigerian movie",
    "Channel": "Uchenna Mbunabo Tv",
    "Category": "Entertainment",
    "Views Gained": 2490658
  },
  {
    "Rank": 13,
    "Change": "0",
    "Thumbnail": "https://i.ytimg.com/vi/cgsdHHKwo1U/hqdefault.jpg",
    "Title": "ALAKADA GEN Z Full Movie | Toyin Abraham, Bolaji Amusan, Imisi | Latest Nollywood Comedy Drama 2026",
    "Channel": "Toyin Abraham TV",
    "Category": "Entertainment",
    "Views Gained": 2287703
  },
  {
    "Rank": 14,
    "Change": "New",
    "Thumbnail": "https://i.ytimg.com/vi/HyY2ffDv5OU/hqdefault.jpg",
    "Title": "CONSTRUIMOS MINECRAFT EN LA VIDA REAL !!",
    "Channel": "Alejo Igoa",
    "Category": "Entertainment",
    "Views Gained": 2167672
  },
  {
    "Rank": 15,
    "Change": "-3",
    "Thumbnail": "https://i.ytimg.com/vi/Jc_zlInukSA/hqdefault.jpg",
    "Title": "Jon Stewart Dissects Trump’s “Art of the Deal” Iran Strategy... That Isn't Working | The Daily Show",
    "Channel": "The Daily Show",
    "Category": "Comedy",
    "Views Gained": 2161525
  },
  {
    "Rank": 16,
    "Change": "-5",
    "Thumbnail": "https://i.ytimg.com/vi/QATdS_RTWWI/hqdefault.jpg",
    "Title": "Uzak Şehir 58. Bölüm",
    "Channel": "Uzak Şehir",
    "Category": "Entertainment",
    "Views Gained": 2049742
  },
  {
    "Rank": 17,
    "Change": "New",
    "Thumbnail": "https://i.ytimg.com/vi/dQlEtJEbO2s/hqdefault.jpg",
    "Title": "QUI TROUVERA LE MEILLEUR CONTAINER ? (ft Joyca, Léna, Djilsi & Maxime Biaggi)",
    "Channel": "SQUEEZIE",
    "Category": "Entertainment",
    "Views Gained": 1928727
  },
  {
    "Rank": 18,
    "Change": "+6",
    "Thumbnail": "https://i.ytimg.com/vi/9md71-I-c44/hqdefault.jpg",
    "Title": "Episodio 370 🚨 - ¿Nacos o Whitexicans? FT. @AldoRendón",
    "Channel": "Slobotzky",
    "Category": "Comedy",
    "Views Gained": 1922496
  },
  {
    "Rank": 19,
    "Change": "New",
    "Thumbnail": "https://i.ytimg.com/vi/pSpiob9D_7I/hqdefault.jpg",
    "Title": "SIDEMEN AMONG US PROXIMITY CHAT BUT THE IMPOSTOR DOESN'T KNOW WHO THE OTHER IMPOSTOR IS",
    "Channel": "MoreSidemen",
    "Category": "People & Blogs",
    "Views Gained": 1896596
  },
  {
    "Rank": 20,
    "Change": "-4",
    "Thumbnail": "https://i.ytimg.com/vi/MZgLdey5dZY/hqdefault.jpg",
    "Title": "J'ai mis Mastu et Byilhan dans la PIRE vidéo YouTube",
    "Channel": "Anyme023",
    "Category": "Entertainment",
    "Views Gained": 1831148
  },
  {
    "Rank": 21,
    "Change": "-11",
    "Thumbnail": "https://i.ytimg.com/vi/zdvwklqyAeU/hqdefault.jpg",
    "Title": "JJ and Mikey WENT INSIDE Friends’ Bodies and SAW EVERYTHING in Minecraft",
    "Channel": "Maizen",
    "Category": "Gaming",
    "Views Gained": 1725909
  },
  {
    "Rank": 22,
    "Change": "-5",
    "Thumbnail": "https://i.ytimg.com/vi/Voo2rvIVbsA/hqdefault.jpg",
    "Title": "Güller ve Günahlar 25. Bölüm - Full Bölüm",
    "Channel": "Güller ve Günahlar",
    "Category": "People & Blogs",
    "Views Gained": 1689145
  },
  {
    "Rank": 23,
    "Change": "-4",
    "Thumbnail": "https://i.ytimg.com/vi/C_TvsFED5gY/hqdefault.jpg",
    "Title": "ON NE DOIT PAS SE FAIRE RECALER ! (Avec Seb et Sofyan)",
    "Channel": "JOYCA",
    "Category": "Entertainment",
    "Views Gained": 1685660
  },
  {
    "Rank": 24,
    "Change": "-18",
    "Thumbnail": "https://i.ytimg.com/vi/P_yLe8taY5A/hqdefault.jpg",
    "Title": "Kızılcık Şerbeti 133. Bölüm @showtv",
    "Channel": "Kızılcık Şerbeti",
    "Category": "Entertainment",
    "Views Gained": 1675260
  },
  {
    "Rank": 25,
    "Change": "-7",
    "Thumbnail": "https://i.ytimg.com/vi/7vVYON6ncD0/hqdefault.jpg",
    "Title": "БАТЯ И ТЁЩА 3 : ВОЙНА ЗА НАСЛЕДСТВО",
    "Channel": "BATEK_OFFICIAL",
    "Category": "Comedy",
    "Views Gained": 1667312
  },
  {
    "Rank": 26,
    "Change": "+21",
    "Thumbnail": "https://i.ytimg.com/vi/C1Lt63LTCJw/hqdefault.jpg",
    "Title": "Sevdiğim Sensin 10. Bölüm",
    "Channel": "Sevdiğim Sensin",
    "Category": "Entertainment",
    "Views Gained": 1650854
  },
  {
    "Rank": 27,
    "Change": "-2",
    "Thumbnail": "https://i.ytimg.com/vi/ZN4njIQcSR4/hqdefault.jpg",
    "Title": "Prediction Markets: Last Week Tonight with John Oliver (HBO)",
    "Channel": "LastWeekTonight",
    "Category": "Entertainment",
    "Views Gained": 1591739
  },
  {
    "Rank": 28,
    "Change": "+12",
    "Thumbnail": "https://i.ytimg.com/vi/CZyI7BcqJCg/hqdefault.jpg",
    "Title": "Azab Penjual Penyetan Ikan Sapu-sapu  (dibilang Patin) | Kartun Animasi Drama Pedagang",
    "Channel": "Rizky Riplay",
    "Category": "Film & Animation",
    "Views Gained": 1583828
  },
  {
    "Rank": 29,
    "Change": "New",
    "Thumbnail": "https://i.ytimg.com/vi/4R_Df1BdICA/hqdefault.jpg",
    "Title": "Kızılcık Şerbeti 134. Bölüm @showtv",
    "Channel": "Kızılcık Şerbeti",
    "Category": "Entertainment",
    "Views Gained": 1546001
  },
  {
    "Rank": 30,
    "Change": "New",
    "Thumbnail": "https://i.ytimg.com/vi/JstGCPsj9wg/hqdefault.jpg",
    "Title": "How Tech Companies Lie to You.",
    "Channel": "Mrwhosetheboss",
    "Category": "Science & Technology",
    "Views Gained": 1488968
  },
  {
    "Rank": 31,
    "Change": "-4",
    "Thumbnail": "https://i.ytimg.com/vi/0FV42j9xSV0/hqdefault.jpg",
    "Title": "Instalé 90 Mods en GTA: San Andreas",
    "Channel": "Rubius Z",
    "Category": "Gaming",
    "Views Gained": 1461677
  },
  {
    "Rank": 32,
    "Change": "-4",
    "Thumbnail": "https://i.ytimg.com/vi/36PjXLyDfzc/hqdefault.jpg",
    "Title": "Iran’s Fleet ‘RUNS THE BLOCKADE’… Trump Wipes It OFF THE MAP",
    "Channel": "Cash Jordan",
    "Category": "People & Blogs",
    "Views Gained": 1446109
  },
  {
    "Rank": 33,
    "Change": "-4",
    "Thumbnail": "https://i.ytimg.com/vi/PCZdfxoZjq4/hqdefault.jpg",
    "Title": "I Survived 100 Days as PROTOTYPE in Minecraft",
    "Channel": "EYstreem",
    "Category": "Gaming",
    "Views Gained": 1434351
  },
  {
    "Rank": 34,
    "Change": "-13",
    "Thumbnail": "https://i.ytimg.com/vi/T4rIpXveUxM/hqdefault.jpg",
    "Title": "Meadowbrook Hearts: The Transition – Their Love Was Tested | Nollywood 2026 Full Movie",
    "Channel": "Vikar Films TV",
    "Category": "Film & Animation",
    "Views Gained": 1426267
  },
  {
    "Rank": 35,
    "Change": "+1",
    "Thumbnail": "https://i.ytimg.com/vi/zlYhlhyx_8k/hqdefault.jpg",
    "Title": "LET HEAVEN FALL - DESTINY ETIKO, LIZZY GOLD, UJU OKOLI, Latest 2026 Nigerian Movie",
    "Channel": "Chinemelu's Channel",
    "Category": "Film & Animation",
    "Views Gained": 1402890
  },
  {
    "Rank": 36,
    "Change": "-5",
    "Thumbnail": "https://i.ytimg.com/vi/G-Aq6XT0Rdc/hqdefault.jpg",
    "Title": "Might Be the Worst Review I've Ever Seen",
    "Channel": "penguinz0",
    "Category": "Entertainment",
    "Views Gained": 1397478
  },
  {
    "Rank": 37,
    "Change": "+2",
    "Thumbnail": "https://i.ytimg.com/vi/7cs0Rs0k-Wg/hqdefault.jpg",
    "Title": "ORIGINAL SIN -FREDERICK LEONARD, STELLA DAMASUS, MICHAEL DAPPA #trending  Full Nigerian Movie 2026.",
    "Channel": "Frederick Leonard TV.",
    "Category": "Entertainment",
    "Views Gained": 1394515
  },
  {
    "Rank": 38,
    "Change": "-4",
    "Thumbnail": "https://i.ytimg.com/vi/Rinm-EETs0U/hqdefault.jpg",
    "Title": "This Drain Clearing Game is INCREDIBLY Satisfying",
    "Channel": "SMii7Y",
    "Category": "Gaming",
    "Views Gained": 1367677
  },
  {
    "Rank": 39,
    "Change": "-4",
    "Thumbnail": "https://i.ytimg.com/vi/DD3FukBF0Ms/hqdefault.jpg",
    "Title": "Una CHICA NINJA me SECUESTRÓ en Minecraft!",
    "Channel": "Dagar",
    "Category": "Gaming",
    "Views Gained": 1359228
  },
  {
    "Rank": 40,
    "Change": "+4",
    "Thumbnail": "https://i.ytimg.com/vi/DAGH-RIdUIU/hqdefault.jpg",
    "Title": "AND THERE WAS YOU ( Official Movie ) : CLINTON JOSHUA, OMECHE OKO, THELMA CHUKWUNWEM, CHUDY IBEKWE.",
    "Channel": "Clinton Joshua Tv",
    "Category": "Film & Animation",
    "Views Gained": 1333750
  },
  {
    "Rank": 41,
    "Change": "New",
    "Thumbnail": "https://i.ytimg.com/vi/NKKOq7XwDyQ/hqdefault.jpg",
    "Title": "We Played Burglin' Gnomes Again...",
    "Channel": "SMii7Y",
    "Category": "Gaming",
    "Views Gained": 1311076
  },
  {
    "Rank": 42,
    "Change": "New",
    "Thumbnail": "https://i.ytimg.com/vi/oUvqgWVz7Nw/hqdefault.jpg",
    "Title": "Die Geschichte vom Drachenlord",
    "Channel": "Jules",
    "Category": "Entertainment",
    "Views Gained": 1298291
  },
  {
    "Rank": 43,
    "Change": "0",
    "Thumbnail": "https://i.ytimg.com/vi/O_uEVCkgT34/hqdefault.jpg",
    "Title": "A TASTE OF KARMA - CHIOMA NWOSU, BRIGHT MORGAN, PRISMA JAMES 2026 Latest Nollywood New Movie",
    "Channel": "NollyFamily tv",
    "Category": "Entertainment",
    "Views Gained": 1219799
  },
  {
    "Rank": 44,
    "Change": "New",
    "Thumbnail": "https://i.ytimg.com/vi/x26A28DoT-w/hqdefault.jpg",
    "Title": "Was I Wrong About the Macbook Neo?",
    "Channel": "Linus Tech Tips",
    "Category": "Science & Technology",
    "Views Gained": 1201689
  },
  {
    "Rank": 45,
    "Change": "-19",
    "Thumbnail": "https://i.ytimg.com/vi/PCCrgqp5rxU/hqdefault.jpg",
    "Title": "Arugba ( The Vessel) - Latest Yoruba Movie 2026 drama | Iteledicon | Kemity | Rotimi Salami | Efun ",
    "Channel": "Itelediconstudio",
    "Category": "Film & Animation",
    "Views Gained": 1185162
  },
  {
    "Rank": 46,
    "Change": "New",
    "Thumbnail": "https://i.ytimg.com/vi/vOSWtDUUFuQ/hqdefault.jpg",
    "Title": "दलबदल या धरपकड़? AAP का साथ छोड़ा राघव चड्ढा ने",
    "Channel": "Ravish Kumar Official",
    "Category": "News & Politics",
    "Views Gained": 1138642
  },
  {
    "Rank": 47,
    "Change": "New",
    "Thumbnail": "https://i.ytimg.com/vi/zpUyg4O9f7U/hqdefault.jpg",
    "Title": "VTECH : Les films Cars ( Ka-chow )",
    "Channel": "Sylvain Lyve",
    "Category": "Autos & Vehicles",
    "Views Gained": 1132060
  },
  {
    "Rank": 48,
    "Change": "New",
    "Thumbnail": "https://i.ytimg.com/vi/xNZLTdz77aM/hqdefault.jpg",
    "Title": "LOVE IN OVERDRIVE - The best Romantic Movie of 2026",
    "Channel": "ChinneyLoveEze Tv",
    "Category": "Entertainment",
    "Views Gained": 1081065
  },
  {
    "Rank": 49,
    "Change": "-34",
    "Thumbnail": "https://i.ytimg.com/vi/S-e4KE626To/hqdefault.jpg",
    "Title": "Birth to Death as a Minecraft Developer",
    "Channel": "ProBoiz 95",
    "Category": "Gaming",
    "Views Gained": 1052911
  },
  {
    "Rank": 50,
    "Change": "New",
    "Thumbnail": "https://i.ytimg.com/vi/W8DbKPlznTg/hqdefault.jpg",
    "Title": "We Joined GUGUGAGA PENGUIN in Roblox!",
    "Channel": "Tyler & Snowi",
    "Category": "Gaming",
    "Views Gained": 1029040
  }
]